pytorch_sphinx_theme2/__init__.py
pytorch_sphinx_theme2/custom_directives.py
pytorch_sphinx_theme2/links.json
pytorch_sphinx_theme2/theme.conf
pytorch_sphinx_theme2/theme_variables.jinja
pytorch_sphinx_theme2/static/css/theme.css
pytorch_sphinx_theme2/static/img/chevron-down-black.svg
pytorch_sphinx_theme2/static/img/chevron-down-light.svg
pytorch_sphinx_theme2/static/img/chevron-right-orange.svg
pytorch_sphinx_theme2/static/img/chevron-right-white.svg
pytorch_sphinx_theme2/static/img/icon-menu-dots-dark.svg
pytorch_sphinx_theme2/static/img/icon-menu-dots.svg
pytorch_sphinx_theme2/static/img/logo-dark.svg
pytorch_sphinx_theme2/static/img/logo-icon.svg
pytorch_sphinx_theme2/static/img/logo-white.svg
pytorch_sphinx_theme2/static/img/logo.svg
pytorch_sphinx_theme2/static/img/pytorch-colab.svg
pytorch_sphinx_theme2/static/img/pytorch-download.svg
pytorch_sphinx_theme2/static/img/pytorch-github.svg
pytorch_sphinx_theme2/static/img/pytorch-logo-dark-unstable.png
pytorch_sphinx_theme2/static/img/pytorch-logo-dark.png
pytorch_sphinx_theme2/static/img/pytorch-logo-dark.svg
pytorch_sphinx_theme2/static/img/pytorch-logo-flame.png
pytorch_sphinx_theme2/static/img/pytorch-logo-flame.svg
pytorch_sphinx_theme2/static/img/pytorch-x.svg
pytorch_sphinx_theme2/static/img/pytorch_seo.png
pytorch_sphinx_theme2/static/js/cookie-banner.js
pytorch_sphinx_theme2/static/js/jquery.min.js
pytorch_sphinx_theme2/static/js/mobile-menu.js
pytorch_sphinx_theme2/static/js/send-feedback.js
pytorch_sphinx_theme2/static/js/star-rating.js
pytorch_sphinx_theme2/static/js/theme.js
pytorch_sphinx_theme2/static/js/tutorial-buttons-call-to-action.js
pytorch_sphinx_theme2/static/js/tutorials-filter-tags.js
pytorch_sphinx_theme2/static/scss/_call_to_action.scss
pytorch_sphinx_theme2/static/scss/_components.scss
pytorch_sphinx_theme2/static/scss/_custom.scss
pytorch_sphinx_theme2/static/scss/_footer.scss
pytorch_sphinx_theme2/static/scss/_google_search.scss
pytorch_sphinx_theme2/static/scss/_layout.scss
pytorch_sphinx_theme2-0.3.0.dist-info/licenses/LICENSE
pytorch_sphinx_theme2-0.3.0.dist-info/METADATA
pytorch_sphinx_theme2-0.3.0.dist-info/WHEEL
pytorch_sphinx_theme2-0.3.0.dist-info/entry_points.txt
pytorch_sphinx_theme2-0.3.0.dist-info/top_level.txt
pytorch_sphinx_theme2-0.3.0.dist-info/RECORD
